jdataclass/__init__.py
jdataclass/jdataclass.py
jdataclass-0.1.1.dist-info/LICENSE
jdataclass-0.1.1.dist-info/METADATA
jdataclass-0.1.1.dist-info/WHEEL
jdataclass-0.1.1.dist-info/RECORD
