Metadata-Version: 2.1
Name: jdataclass
Version: 0.1.1
Summary: jdataclass is a Python module that extends the functionality of Python's native dataclasses by allowing custom mappings for reading from dataclass objects and writing to other objects during serialization and deserialization. With jdataclass, you can easily control how data is mapped between your dataclass and external data sources like JSON, databases, or other data formats.
Author: Guilherme Vidal
Author-email: guilherme.pereira.vidal@gmail.com
Requires-Python: >=3.9,<4.0
Classifier: Programming Language :: Python :: 3
Classifier: Programming Language :: Python :: 3.9
Classifier: Programming Language :: Python :: 3.10
Classifier: Programming Language :: Python :: 3.11
